maja_newsletter/models.py
maja_newsletter/tasks.py
maja_newsletter/__init__.py
maja_newsletter/settings.py
maja_newsletter/testsettings.py
maja_newsletter/managers.py
maja_newsletter/tests.py
maja_newsletter/mailer.py
maja_newsletter/forms.py
maja_newsletter/cmsplugin_newsletter/models.py
maja_newsletter/cmsplugin_newsletter/__init__.py
maja_newsletter/cmsplugin_newsletter/settings.py
maja_newsletter/cmsplugin_newsletter/cms_plugins.py
maja_newsletter/cmsplugin_newsletter/migrations/__init__.py
maja_newsletter/cmsplugin_newsletter/migrations/0001_initial.py
maja_newsletter/cmsplugin_newsletter/migrations/0002_rename_tables.py
maja_newsletter/urls/tinymce.py
maja_newsletter/urls/tracking.py
maja_newsletter/urls/__init__.py
maja_newsletter/urls/mailing_list.py
maja_newsletter/urls/statistics.py
maja_newsletter/urls/ckeditor.py
maja_newsletter/urls/newsletter.py
maja_newsletter/management/__init__.py
maja_newsletter/management/commands/send_newsletter_continuous.py
maja_newsletter/management/commands/__init__.py
maja_newsletter/management/commands/send_newsletter.py
maja_newsletter/static/edn/js/jquery.form.js
maja_newsletter/static/edn/js/jquery.heatcolor.js
maja_newsletter/static/edn/js/jquery.js
maja_newsletter/static/edn/js/swfobject/swfobject.js
maja_newsletter/static/edn/js/swfobject/expressInstall.swf
maja_newsletter/static/edn/js/swfobject/index_dynamic.html
maja_newsletter/static/edn/js/swfobject/index.html
maja_newsletter/static/edn/js/swfobject/test.swf
maja_newsletter/static/edn/swf/open-flash-chart.swf
maja_newsletter/views/tracking.py
maja_newsletter/views/__init__.py
maja_newsletter/views/ckeditor_utils.py
maja_newsletter/views/mailing_list.py
maja_newsletter/views/statistics.py
maja_newsletter/views/tinymce_utils.py
maja_newsletter/views/newsletter.py
maja_newsletter/templates/newsletter/newsletter_detail.html
maja_newsletter/templates/newsletter/newsletter_image_tracking.html
django_maja_newsletter-0.6.0.dist-info/metadata.json
django_maja_newsletter-0.6.0.dist-info/RECORD
django_maja_newsletter-0.6.0.dist-info/METADATA
django_maja_newsletter-0.6.0.dist-info/DESCRIPTION.rst
django_maja_newsletter-0.6.0.dist-info/top_level.txt
django_maja_newsletter-0.6.0.dist-info/WHEEL
