Metadata-Version: 2.0
Name: django-maja-newsletter
Version: 0.6.0
Summary: A Django app for sending newsletter by email to a contact list.
Home-page: http://nephila.it/
Author: Iacopo Spalletti
Author-email: i.spalletti@nephila.it
License: BSD License
Keywords: django,newsletter,mailing
Platform: UNKNOWN
Classifier: Framework :: Django
Classifier: Programming Language :: Python
Classifier: Environment :: Web Environment
Classifier: Intended Audience :: Developers
Classifier: Operating System :: OS Independent
Classifier: License :: OSI Approved :: BSD License
Classifier: Development Status :: 5 - Production/Stable
Classifier: Topic :: Software Development :: Libraries :: Python Modules
Requires-Dist: setuptools
Requires-Dist: html2text
Requires-Dist: python-dateutil (==1.5)
Requires-Dist: BeautifulSoup
Requires-Dist: django-tagging
Requires-Dist: vobject
Requires-Dist: xlwt
Requires-Dist: xlrd
Requires-Dist: django-filebrowser-no-grappelli-nph
Requires-Dist: premailer
Requires-Dist: pytz
Requires-Dist: celery (>=3.1,<3.2)
